[
  {
    "id": "R1",
    "category": "قوانين",
    "name": "صحيفة أم القرى",
    "authority": "وزارة الإعلام",
    "description": "الجريدة الرسمية للمملكة العربية السعودية، تنشر الأنظمة والمراسيم الملكية واللوائح التنفيذية فور اعتمادها.",
    "url": "https://uqn.gov.sa"
  },
  {
    "id": "R2",
    "category": "قوانين",
    "name": "هيئة الخبراء بمجلس الوزراء",
    "authority": "مجلس الوزراء",
    "description": "المرجع التشريعي الرسمي الذي يحفظ الأنظمة واللوائح بعد نشرها في أم القرى.",
    "url": "https://laws.boe.gov.sa"
  },
  {
    "id": "R3",
    "category": "لوائح",
    "name": "الوزارات القطاعية (العدل، الموارد البشرية، التجارة)",
    "authority": "الجهات التنفيذية",
    "description": "تصدر اللوائح التنفيذية التفصيلية لتطبيق الأنظمة حسب اختصاصها القضائي والعمالي والتجاري.",
    "url": "https://www.moj.gov.sa"
  },
  {
    "id": "R4",
    "category": "تعاميم",
    "name": "البنك المركزي السعودي (SAMA)",
    "authority": "SAMA",
    "description": "يصدر التعاميم والتعليمات للقطاع المالي، التأميني، وشركات التمويل لضمان الامتثال والإشراف المالي.",
    "url": "https://www.sama.gov.sa"
  },
  {
    "id": "R5",
    "category": "تعاميم",
    "name": "هيئة السوق المالية (CMA)",
    "authority": "CMA",
    "description": "تنشر التعاميم والتعليمات الخاصة بالشركات المساهمة والوسطاء والمستشارين الماليين.",
    "url": "https://cma.org.sa"
  },
  {
    "id": "R6",
    "category": "تعاميم",
    "name": "هيئة الزكاة والضريبة والجمارك (ZATCA)",
    "authority": "ZATCA",
    "description": "تصدر التعاميم الخاصة بالزكاة، الضرائب، الجمارك، والفوترة الإلكترونية.",
    "url": "https://zatca.gov.sa"
  },
  {
    "id": "R7",
    "category": "سوابق قضائية",
    "name": "وزارة العدل",
    "authority": "MOJ",
    "description": "تنشر السوابق القضائية في القضاء العام والتجاري والعمالي عبر بوابة الأحكام القضائية.",
    "url": "https://judgments.moj.gov.sa"
  },
  {
    "id": "R8",
    "category": "سوابق قضائية",
    "name": "ديوان المظالم",
    "authority": "ديوان المظالم",
    "description": "ينشر السوابق القضائية في القضاء الإداري والطعون على القرارات الحكومية والعقود الإدارية.",
    "url": "https://www.bog.gov.sa"
  },
  {
    "id": "R9",
    "category": "سوابق قضائية",
    "name": "لجان المنازعات المصرفية والتمويلية (SAMA)",
    "authority": "SAMA",
    "description": "تصدر أحكامًا شبه قضائية تخص نزاعات البنوك وشركات التمويل وشركات التأمين الخاضعة لإشراف البنك المركزي.",
    "url": "https://www.sama.gov.sa"
  },
  {
    "id": "R10",
    "category": "سوابق قضائية",
    "name": "لجان الفصل في منازعات الأوراق المالية (CMA)",
    "authority": "CMA",
    "description": "تنشر السوابق القضائية الخاصة بالمخالفات المالية وحوكمة الشركات والإفصاح.",
    "url": "https://cma.org.sa"
  },
  {
    "id": "R11",
    "category": "سوابق قضائية",
    "name": "اللجان الضريبية والجمركية (ZATCA)",
    "authority": "ZATCA",
    "description": "تصدر أحكامًا في المنازعات الضريبية والجمركية وتشكل مرجعًا لاجتهادات الضرائب والجمارك.",
    "url": "https://zatca.gov.sa"
  },
  {
    "id": "R12",
    "category": "سوابق قضائية",
    "name": "اللجان التأمينية (CHI)",
    "authority": "CHI",
    "description": "تنشر الأحكام الصادرة في منازعات التأمين الصحي بين الشركات والمستفيدين ومقدمي الخدمات الطبية.",
    "url": "https://chi.gov.sa"
  },
  {
    "id": "R13",
    "category": "حوكمة والتزام",
    "name": "هيئة السوق المالية (CMA)",
    "authority": "CMA",
    "description": "تنظم حوكمة الشركات والإفصاح والالتزام المؤسسي في السوق المالية السعودية.",
    "url": "https://cma.org.sa"
  },
  {
    "id": "R14",
    "category": "حوكمة والتزام",
    "name": "البنك المركزي السعودي (SAMA)",
    "authority": "SAMA",
    "description": "يصدر اللوائح الخاصة بالحوكمة المصرفية ومكافحة غسل الأموال وإدارة المخاطر المالية.",
    "url": "https://www.sama.gov.sa"
  },
  {
    "id": "R15",
    "category": "حوكمة والتزام",
    "name": "وزارة التجارة (MC)",
    "authority": "MC",
    "description": "تنظم امتثال الشركات التجارية ولوائح الحوكمة الداخلية والتقارير النظامية.",
    "url": "https://mci.gov.sa"
  },
  {
    "id": "R16",
    "category": "حوكمة والتزام",
    "name": "الهيئة السعودية للبيانات والذكاء الاصطناعي (SDAIA) + الهيئة الوطنية للأمن السيبراني (NCA)",
    "authority": "SDAIA / NCA",
    "description": "تصدر لوائح حوكمة البيانات، الذكاء الاصطناعي، وضوابط الأمن السيبراني الوطنية.",
    "url": "https://sdaia.gov.sa"
  },
  {
    "id": "R17",
    "category": "قواعد تنظيمية",
    "name": "البنك المركزي السعودي (SAMA)",
    "authority": "SAMA",
    "description": "يضع القواعد التنفيذية والتراخيص للأنشطة المالية والتأمينية والتمويلية، وينظم الإشراف والرقابة.",
    "url": "https://www.sama.gov.sa"
  },
  {
    "id": "R18",
    "category": "قواعد تنظيمية",
    "name": "هيئة السوق المالية (CMA)",
    "authority": "CMA",
    "description": "تنشر القواعد الإجرائية لتسجيل الشركات، الإفصاح، التداول، والإجراءات التأديبية.",
    "url": "https://cma.org.sa"
  },
  {
    "id": "R19",
    "category": "قواعد تنظيمية",
    "name": "هيئة الزكاة والضريبة والجمارك (ZATCA)",
    "authority": "ZATCA",
    "description": "تنشر القواعد الإجرائية المتعلقة بالضرائب والجمارك والفوترة الإلكترونية.",
    "url": "https://zatca.gov.sa"
  },
  {
    "id": "R20",
    "category": "ضوابط تنظيمية",
    "name": "مجلس الضمان الصحي (CHI)",
    "authority": "CHI",
    "description": "يصدر ضوابط التأمين الصحي الإلزامي ولوائح مقدمي الخدمات الطبية.",
    "url": "https://chi.gov.sa"
  },
  {
    "id": "R21",
    "category": "ضوابط تنظيمية",
    "name": "الهيئة الوطنية للأمن السيبراني (NCA)",
    "authority": "NCA",
    "description": "تصدر ضوابط الأمن السيبراني القطاعية (CSF، ECC، CCC) التي تنظم الامتثال السيبراني في الجهات الحكومية والخاصة.",
    "url": "https://nca.gov.sa"
  }
]